niess/__about__.py
niess/__init__.py
niess/mccode.py
niess/spatial.py
niess/utilities.py
niess/bifrost/__init__.py
niess/bifrost/analyzer.py
niess/bifrost/arm.py
niess/bifrost/bifrost.py
niess/bifrost/channel.py
niess/bifrost/combine.py
niess/bifrost/guide_closing.py
niess/bifrost/guide_compressor.py
niess/bifrost/guide_curved.py
niess/bifrost/guide_expanding.py
niess/bifrost/guide_straight.py
niess/bifrost/guide_tools.py
niess/bifrost/parameters.py
niess/bifrost/primary.py
niess/bifrost/rowland.py
niess/bifrost/tank.py
niess/bifrost/triplet.py
niess/components/__init__.py
niess/components/aperture.py
niess/components/chopper.py
niess/components/collimator.py
niess/components/component.py
niess/components/crystals.py
niess/components/detectors.py
niess/components/filter.py
niess/components/guide.py
niess/components/moderator.py
niess/components/monitors.py
niess/components/secondary.py
niess/components/section.py
niess/components/source.py
niess/cspec/__init__.py
niess/cspec/cspec.py
niess/cspec/pack.py
niess/cspec/parameters.py
niess/cspec/tank.py
niess/io/__init__.py
niess/io/json.py
niess/io/markdown.py
niess/io/mccode.py
niess/io/msgpack.py
niess/io/scipp.py
niess/io/utils.py
niess-0.1.5.dist-info/METADATA
niess-0.1.5.dist-info/WHEEL
niess-0.1.5.dist-info/licenses/LICENSE
niess-0.1.5.dist-info/RECORD
