Metadata-Version: 2.4
Name: niess
Version: 0.1.5
Project-URL: Documentation, https://github.com/g5t/niess#readme
Project-URL: Issues, https://github.com/g5t/niess/issues
Project-URL: Source, https://github.com/g5t/niess
Author-email: Gregory Tucker <gregory.tucker@ess.eu>
License-Expression: BSD-3-Clause
License-File: LICENSE
Classifier: Development Status :: 4 - Beta
Classifier: Programming Language :: Python
Classifier: Programming Language :: Python :: 3.10
Classifier: Programming Language :: Python :: 3.11
Classifier: Programming Language :: Python :: 3.12
Classifier: Programming Language :: Python :: 3.13
Classifier: Programming Language :: Python :: Implementation :: CPython
Classifier: Programming Language :: Python :: Implementation :: PyPy
Requires-Python: >=3.10
Requires-Dist: mccode-antlr>=0.17.0
Requires-Dist: mccode-to-kafka>=0.2.2
Requires-Dist: msgspec>=0.20.0
Requires-Dist: ncrystal>=4.2.4
Requires-Dist: networkx>=3.6
Requires-Dist: numpy
Requires-Dist: scipp>=25.11.0
Requires-Dist: scipy
